lazy_toolkit_pandas/__init__.py
lazy_toolkit_pandas/pandas.py
lazy_toolkit_pandas-0.0.1.dist-info/LICENSE
lazy_toolkit_pandas-0.0.1.dist-info/METADATA
lazy_toolkit_pandas-0.0.1.dist-info/WHEEL
lazy_toolkit_pandas-0.0.1.dist-info/top_level.txt
lazy_toolkit_pandas-0.0.1.dist-info/RECORD
